XeroGraph/__init__.py
XeroGraph/compare.py
XeroGraph/main.py
XeroGraph/utils.py
XeroGraph/xputer_main.py
XeroGraph/data/ACTG175.txt
XeroGraph/data/AML.csv
XeroGraph/data/Breast_cancer.csv
XeroGraph/data/PIMA_Indian.csv
XeroGraph/data/Student_dropout.csv
XeroGraph/data/data_mar.csv
XeroGraph/data/data_mcar.csv
XeroGraph/data/data_mnar.csv
XeroGraph-0.0.11.dist-info/LICENSE
XeroGraph-0.0.11.dist-info/METADATA
XeroGraph-0.0.11.dist-info/WHEEL
XeroGraph-0.0.11.dist-info/top_level.txt
XeroGraph-0.0.11.dist-info/RECORD
